jsonpath_expression/__init__.py
jsonpath_expression/jsonpath_expression.py
jsonpath_expression/test_jsonpath_expression.py
jsonpath_expression-1.0.dist-info/METADATA
jsonpath_expression-1.0.dist-info/WHEEL
jsonpath_expression-1.0.dist-info/top_level.txt
jsonpath_expression-1.0.dist-info/RECORD
