Metadata-Version: 2.1
Name: jsonpath-expression
Version: 1.0
Summary: jsonpath expression generate
Home-page: https://gitee.com/ishuzf/jsonpath_expression
Author: shuzhifu
Author-email: ishuzf@163.com
License: UNKNOWN
Platform: UNKNOWN
Classifier: Programming Language :: Python :: 3
Classifier: License :: OSI Approved :: MIT License
Classifier: Operating System :: OS Independent
Requires-Dist: jsonpath (>=0.82)
